{
  "AOR": {
    "width": 1280,
    "height": 536
  },
  "AQ": {
    "width": 2770,
    "height": 589
  },
  "AR": {
    "width": 1213,
    "height": 351
  },
  "ASC": {
    "width": 4000,
    "height": 2025
  },
  "ASR": {
    "width": 731,
    "height": 250
  },
  "B2": {
    "width": 1025,
    "height": 1109
  },
  "BCR": {
    "width": 588,
    "height": 221
  },
  "BKP": {
    "width": 1280,
    "height": 271
  },
  "BKT": {
    "width": 1280,
    "height": 445
  },
  "BLK": {
    "width": 1920,
    "height": 1199
  },
  "BLW": {
    "width": 1280,
    "height": 133
  },
  "BRS": {
    "width": 1280,
    "height": 529
  },
  "BST": {
    "width": 1280,
    "height": 422
  },
  "BUS": {
    "width": 1280,
    "height": 448
  },
  "CEC": {
    "width": 1280,
    "height": 614
  },
  "CEL": {
    "width": 557,
    "height": 130
  },
  "CES": {
    "width": 1280,
    "height": 617
  },
  "CG": {
    "width": 204,
    "height": 98
  },
  "CIN": {
    "width": 1280,
    "height": 503
  },
  "CL": {
    "width": 845,
    "height": 200
  },
  "CPA": {
    "width": 1280,
    "height": 464
  },
  "CRE": {
    "width": 1280,
    "height": 680
  },
  "CRI": {
    "width": 1920,
    "height": 548
  },
  "CRZ": {
    "width": 720,
    "height": 272
  },
  "DAA": {
    "width": 1280,
    "height": 345
  },
  "DCR": {
    "width": 575,
    "height": 254
  },
  "DET": {
    "width": 2798,
    "height": 1375
  },
  "DEX": {
    "width": 588,
    "height": 169
  },
  "DF": {
    "width": 1080,
    "height": 284
  },
  "DP": {
    "width": 654,
    "height": 110
  },
  "DR": {
    "width": 562,
    "height": 84
  },
  "DRI": {
    "width": 1920,
    "height": 714
  },
  "DRM": {
    "width": 1280,
    "height": 664
  },
  "DRV": {
    "width": 575,
    "height": 155
  },
  "DRX": {
    "width": 554,
    "height": 171
  },
  "DS": {
    "width": 1280,
    "height": 323
  },
  "DX": {
    "width": 573,
    "height": 132
  },
  "EM": {
    "width": 210,
    "height": 33
  },
  "EPO": {
    "width": 1280,
    "height": 298
  },
  "EVO": {
    "width": 1280,
    "height": 308
  },
  "EVS": {
    "width": 1280,
    "height": 513
  },
  "EX": {
    "width": 1080,
    "height": 247
  },
  "FCO": {
    "width": 1280,
    "height": 374
  },
  "FFI": {
    "width": 1280,
    "height": 504
  },
  "FLF": {
    "width": 1280,
    "height": 526
  },
  "FLI": {
    "width": 1280,
    "height": 671
  },
  "FO": {
    "width": 1337,
    "height": 1121
  },
  "FST": {
    "width": 1280,
    "height": 519
  },
  "G1": {
    "width": 2404,
    "height": 1120
  },
  "G2": {
    "width": 1280,
    "height": 569
  },
  "GE": {
    "width": 582,
    "height": 130
  },
  "GEN": {
    "width": 578,
    "height": 126
  },
  "GRI": {
    "width": 1280,
    "height": 470
  },
  "HIF": {
    "width": 1280,
    "height": 587
  },
  "HL": {
    "width": 575,
    "height": 305
  },
  "HP": {
    "width": 195,
    "height": 98
  },
  "HS": {
    "width": 997,
    "height": 418
  },
  "JTG": {
    "width": 2027,
    "height": 637
  },
  "JU": {
    "width": 1360,
    "height": 1112
  },
  "KSS": {
    "width": 580,
    "height": 198
  },
  "LA": {
    "width": 600,
    "height": 164
  },
  "LC": {
    "width": 2656,
    "height": 1030
  },
  "LM": {
    "width": 578,
    "height": 210
  },
  "LOR": {
    "width": 720,
    "height": 278
  },
  "LOT": {
    "width": 1280,
    "height": 420
  },
  "LTR": {
    "width": 1280,
    "height": 365
  },
  "MA": {
    "width": 578,
    "height": 145
  },
  "MD": {
    "width": 577,
    "height": 147
  },
  "MEG": {
    "width": 1920,
    "height": 386
  },
  "MEW": {
    "width": 1201,
    "height": 912
  },
  "MT": {
    "width": 581,
    "height": 152
  },
  "N1": {
    "width": 1280,
    "height": 422
  },
  "N2": {
    "width": 2148,
    "height": 986
  },
  "N3": {
    "width": 1526,
    "height": 1348
  },
  "N4": {
    "width": 2220,
    "height": 1050
  },
  "NVI": {
    "width": 1280,
    "height": 296
  },
  "NXD": {
    "width": 1512,
    "height": 506
  },
  "OBF": {
    "width": 1194,
    "height": 481
  },
  "PAF": {
    "width": 1200,
    "height": 656
  },
  "PAL": {
    "width": 892,
    "height": 294
  },
  "PAR": {
    "width": 1200,
    "height": 398
  },
  "PBL": {
    "width": 1920,
    "height": 527
  },
  "PFL": {
    "width": 1920,
    "height": 833
  },
  "PGO": {
    "width": 900,
    "height": 565
  },
  "PHF": {
    "width": 1280,
    "height": 615
  },
  "PK": {
    "width": 206,
    "height": 92
  },
  "PL": {
    "width": 1116,
    "height": 216
  },
  "PLB": {
    "width": 513,
    "height": 136
  },
  "PLF": {
    "width": 1280,
    "height": 321
  },
  "PLS": {
    "width": 1280,
    "height": 288
  },
  "POR": {
    "width": 1920,
    "height": 854
  },
  "PRC": {
    "width": 1280,
    "height": 430
  },
  "PRE": {
    "width": 3438,
    "height": 1593
  },
  "RCL": {
    "width": 1280,
    "height": 459
  },
  "RG": {
    "width": 186,
    "height": 108
  },
  "ROS": {
    "width": 1280,
    "height": 580
  },
  "RR": {
    "width": 577,
    "height": 170
  },
  "RS": {
    "width": 581,
    "height": 85
  },
  "SCR": {
    "width": 5600,
    "height": 2074
  },
  "SF": {
    "width": 600,
    "height": 186
  },
  "SFA": {
    "width": 1830,
    "height": 860
  },
  "SHF": {
    "width": 1280,
    "height": 633
  },
  "SIT": {
    "width": 621,
    "height": 291
  },
  "SK": {
    "width": 2814,
    "height": 930
  },
  "SLG": {
    "width": 1280,
    "height": 499
  },
  "SS": {
    "width": 572,
    "height": 76
  },
  "SSH": {
    "width": 1280,
    "height": 250
  },
  "SSP": {
    "width": 1201,
    "height": 531
  },
  "STS": {
    "width": 1280,
    "height": 426
  },
  "SUM": {
    "width": 1280,
    "height": 289
  },
  "SV": {
    "width": 1126,
    "height": 320
  },
  "SVI": {
    "width": 898,
    "height": 260
  },
  "SW": {
    "width": 1080,
    "height": 299
  },
  "TEF": {
    "width": 1199,
    "height": 474
  },
  "TEU": {
    "width": 1280,
    "height": 472
  },
  "TM": {
    "width": 1280,
    "height": 333
  },
  "TR": {
    "width": 400,
    "height": 137
  },
  "TRR": {
    "width": 192,
    "height": 80
  },
  "TWM": {
    "width": 1225,
    "height": 523
  },
  "UD": {
    "width": 1280,
    "height": 304
  },
  "UF": {
    "width": 571,
    "height": 215
  },
  "UL": {
    "width": 1280,
    "height": 290
  },
  "UNB": {
    "width": 1006,
    "height": 421
  },
  "UNM": {
    "width": 1280,
    "height": 597
  },
  "UPR": {
    "width": 1280,
    "height": 537
  },
  "VIV": {
    "width": 1280,
    "height": 509
  },
  "XY": {
    "width": 1280,
    "height": 321
  }
}